{ 
	"tips": [
		{
		"name": "Baro",
		"item": [
			{"position": 1,
			"team": "Malmö FF"},
			{"position": 2,
			"team": "IFK Norrköping"},
			{"position": 3,
			"team": "IFK Göteborg"},
			{"position": 4,
			"team": "AIK"},
			{"position": 5,
			"team": "IF Elfsborg"},
			{"position": 6,
			"team": "BK Häcken"},
			{"position": 7,
			"team": "Örebro"},
			{"position": 8,
			"team": "Kalmar FF"},
			{"position": 9,
			"team": "Hammarby IF"},
			{"position": 10,
			"team": "Djurgårdens IF"},
			{"position": 11,
			"team": "Helsingborgs IF"},
			{"position": 12,
			"team": "Gefle IF"},
			{"position": 13,
			"team": "GIF Sundsvall"},
			{"position": 14,
			"team": "Falkenbergs FF"},
			{"position": 15,
			"team": "Östersunds FK"},
			{"position": 16,
			"team": "Jönköpings Södra IF"}
			]
		},
		{
		"name": "Olle",
		"item": [
			{"position": 1,
			"team": "Malmö FF"},
			{"position": 2,
			"team": "IFK Göteborg"},
			{"position": 3,
			"team": "Örebro"},
			{"position": 4,
			"team": "AIK"},
			{"position": 5,
			"team": "IFK Norrköping"},
			{"position": 6,
			"team": "BK Häcken"},
			{"position": 7,
			"team": "Djurgårdens IF"},
			{"position": 8,
			"team": "IF Elfsborg"},
			{"position": 9,
			"team": "Kalmar FF"},
			{"position": 10,
			"team": "Helsingborgs IF"},
			{"position": 11,
			"team": "Hammarby IF"},
			{"position": 12,
			"team": "Gefle IF"},
			{"position": 13,
			"team": "Östersunds FK"},
			{"position": 14,
			"team": "GIF Sundsvall"},
			{"position": 15,
			"team": "Falkenbergs FF"},
			{"position": 16,
			"team": "Jönköpings Södra IF"}
		]	
		},
		{
		"name": "Alfred",
		"item": [
			{"position": 1,
			"team": "BK Häcken"},
			{"position": 2,
			"team": "IFK Norrköping"},
			{"position": 3,
			"team": "Malmö FF"},
			{"position": 4,
			"team": "IF Elfsborg"},
			{"position": 5,
			"team": "AIK"},
			{"position": 6,
			"team": "Örebro"},
			{"position": 7,
			"team": "IFK Göteborg"},
			{"position": 8,
			"team": "Hammarby IF"},
			{"position": 9,
			"team": "Östersunds FK"},
			{"position": 10,
			"team": "Djurgårdens IF"},
			{"position": 11,
			"team": "Jönköpings Södra IF"},
			{"position": 12,
			"team": "Helsingborgs IF"},
			{"position": 13,
			"team": "GIF Sundsvall"},
			{"position": 14,
			"team": "Gefle IF"},
			{"position": 15,
			"team": "Falkenbergs FF"},
			{"position": 16,
			"team": "Kalmar FF"}
		]	
		}
	]
}
